sportsapi/__init__.py
sportsapi/providers/__init__.py
sportsapi/providers/catapult/__init__.py
sportsapi/providers/catapult/api.py
sportsapi-0.3.0.dist-info/LICENCE
sportsapi-0.3.0.dist-info/METADATA
sportsapi-0.3.0.dist-info/WHEEL
sportsapi-0.3.0.dist-info/top_level.txt
sportsapi-0.3.0.dist-info/RECORD
